glmpynet/__init__.py
glmpynet/__main__.py
glmpynet/_version.py
glmpynet/logistic_regression.py
glmpynet/binding/__init__.py
glmpynet/binding/base.py
glmpynet/binding/mock.py
glmpynet-0.5.8.dist-info/licenses/LICENSE
glmpynet-0.5.8.dist-info/METADATA
glmpynet-0.5.8.dist-info/WHEEL
glmpynet-0.5.8.dist-info/entry_points.txt
glmpynet-0.5.8.dist-info/top_level.txt
glmpynet-0.5.8.dist-info/RECORD
