Metadata-Version: 2.4
Name: glmpynet
Version: 0.5.8
Summary: A scikit-learn compatible wrapper for glmnet-based logistic regression.
Author-email: Rolf Carlson <hrolfrc@gmail.com>
License: Copyright (c) 2025 Rolf Carlson
Project-URL: Homepage, https://github.com/hrolfrc/glmpynet
Project-URL: Repository, https://github.com/hrolfrc/glmpynet
Project-URL: Documentation, https://glmpynet.readthedocs.io
Classifier: Programming Language :: Python :: 3
Classifier: Operating System :: OS Independent
Classifier: Intended Audience :: Science/Research
Classifier: Topic :: Scientific/Engineering :: Artificial Intelligence
Classifier: Topic :: Scientific/Engineering :: Information Analysis
Requires-Python: >=3.8
License-File: LICENSE
Requires-Dist: numpy
Requires-Dist: pandas
Requires-Dist: scikit-learn
Requires-Dist: pybind11>=2.12.0
Provides-Extra: dev
Requires-Dist: pytest; extra == "dev"
Requires-Dist: pytest-cov; extra == "dev"
Requires-Dist: pytest-mock; extra == "dev"
Requires-Dist: sphinx; extra == "dev"
Requires-Dist: sphinx_rtd_theme; extra == "dev"
Requires-Dist: nbsphinx; extra == "dev"
Requires-Dist: pybind11; extra == "dev"
Dynamic: license-file
